{"source": {"viewCount": 15, "name": "2008 Xmas List", "nrow": 10, "id": "5phf-ygbu", "portal": "opendata.socrata.com", "downloadCount": 75, "ncol": 3, "modifyingViewUid": null, "createdAt": 1229016062, "description": "Gift assignments and ideas"}, "datasets": [{"viewCount": 15, "name": "2008 Xmas List", "nrow": 10, "id": "5phf-ygbu", "portal": "opendata.socrata.com", "downloadCount": 75, "ncol": 3, "modifyingViewUid": null, "createdAt": 1229016062, "description": "Gift assignments and ideas"}]}