{"source": {"viewCount": 259, "name": "iPhones sales by Quarter", "nrow": 21, "id": "vwdk-ipzk", "portal": "opendata.socrata.com", "downloadCount": 96, "ncol": 6, "modifyingViewUid": null, "createdAt": 1234300307, "description": "Quarterly iPhone sales figures"}, "datasets": [{"viewCount": 259, "name": "iPhones sales by Quarter", "nrow": 21, "id": "vwdk-ipzk", "portal": "opendata.socrata.com", "downloadCount": 96, "ncol": 6, "modifyingViewUid": null, "createdAt": 1234300307, "description": "Quarterly iPhone sales figures"}]}