{"source": {"viewCount": 150, "name": "Voti Giornata 25", "nrow": 336, "id": "3xk4-pcpk", "portal": "opendata.socrata.com", "downloadCount": 62, "ncol": 15, "modifyingViewUid": null, "createdAt": 1235583214, "description": "Tutti i voti della Giornata 25 di Serie A dati dalla Gazzetta dello Sport."}, "datasets": [{"viewCount": 150, "name": "Voti Giornata 25", "nrow": 336, "id": "3xk4-pcpk", "portal": "opendata.socrata.com", "downloadCount": 62, "ncol": 15, "modifyingViewUid": null, "createdAt": 1235583214, "description": "Tutti i voti della Giornata 25 di Serie A dati dalla Gazzetta dello Sport."}]}