{"source": {"viewCount": 31, "name": "Plans", "nrow": 6, "id": "6hkb-45su", "portal": "opendata.socrata.com", "downloadCount": 59, "ncol": 7, "modifyingViewUid": null, "createdAt": 1237345313, "description": "What CMCers are planning to do this summer and in the future."}, "datasets": [{"viewCount": 31, "name": "Plans", "nrow": 6, "id": "6hkb-45su", "portal": "opendata.socrata.com", "downloadCount": 59, "ncol": 7, "modifyingViewUid": null, "createdAt": 1237345313, "description": "What CMCers are planning to do this summer and in the future."}]}