{"source": {"viewCount": 15, "name": "Planner", "nrow": 48, "id": "pw36-ayx8", "portal": "opendata.socrata.com", "downloadCount": 6, "ncol": 2, "modifyingViewUid": null, "createdAt": 1238363554, "description": "Daily by the half hour list of things to do"}, "datasets": [{"viewCount": 15, "name": "Planner", "nrow": 48, "id": "pw36-ayx8", "portal": "opendata.socrata.com", "downloadCount": 6, "ncol": 2, "modifyingViewUid": null, "createdAt": 1238363554, "description": "Daily by the half hour list of things to do"}]}