{"source": {"viewCount": 400, "name": "Energy Intensity Of Transit Motor Buses (Updated December 2008)", "nrow": 12, "id": "d8yg-7u8d", "portal": "opendata.socrata.com", "downloadCount": 239, "ncol": 24, "modifyingViewUid": null, "createdAt": 1243026149, "description": null}, "datasets": [{"viewCount": 400, "name": "Energy Intensity Of Transit Motor Buses (Updated December 2008)", "nrow": 12, "id": "d8yg-7u8d", "portal": "opendata.socrata.com", "downloadCount": 239, "ncol": 24, "modifyingViewUid": null, "createdAt": 1243026149, "description": null}]}