{"source": {"viewCount": 386, "name": "Federal Exhaust Emissions Certification Standards For Newly Manufactured Gasoline- And Diesel- Powered Heavy Heavy- Duty Trucks ( Grams Per Brake Horsepower-hour)", "nrow": 41, "id": "8jf4-yckx", "portal": "opendata.socrata.com", "downloadCount": 262, "ncol": 16, "modifyingViewUid": null, "createdAt": 1243026205, "description": null}, "datasets": [{"viewCount": 386, "name": "Federal Exhaust Emissions Certification Standards For Newly Manufactured Gasoline- And Diesel- Powered Heavy Heavy- Duty Trucks ( Grams Per Brake Horsepower-hour)", "nrow": 41, "id": "8jf4-yckx", "portal": "opendata.socrata.com", "downloadCount": 262, "ncol": 16, "modifyingViewUid": null, "createdAt": 1243026205, "description": null}]}