{"source": {"viewCount": 527, "name": "U.S. Passenger-Miles (Updated October 2008)", "nrow": 72, "id": "fnbi-nhmp", "portal": "opendata.socrata.com", "downloadCount": 270, "ncol": 24, "modifyingViewUid": null, "createdAt": 1243026502, "description": null}, "datasets": [{"viewCount": 527, "name": "U.S. Passenger-Miles (Updated October 2008)", "nrow": 72, "id": "fnbi-nhmp", "portal": "opendata.socrata.com", "downloadCount": 270, "ncol": 24, "modifyingViewUid": null, "createdAt": 1243026502, "description": null}]}