{"source": {"viewCount": 289, "name": "Chicago Demolition Permits (October)", "nrow": 30, "id": "deyz-qdtz", "portal": "opendata.socrata.com", "downloadCount": 134, "ncol": 33, "modifyingViewUid": null, "createdAt": 1256675458, "description": "Demolition permits for the month of October"}, "datasets": [{"viewCount": 289, "name": "Chicago Demolition Permits (October)", "nrow": 30, "id": "deyz-qdtz", "portal": "opendata.socrata.com", "downloadCount": 134, "ncol": 33, "modifyingViewUid": null, "createdAt": 1256675458, "description": "Demolition permits for the month of October"}]}