{"source": {"viewCount": 167, "name": "Continuity of Operations - Important Files", "nrow": 5, "id": "6bqr-ydh3", "portal": "opendata.socrata.com", "downloadCount": 145, "ncol": 6, "modifyingViewUid": null, "createdAt": 1279586535, "description": "These are critical files that we need backed up offsite. We're using Socrata's cloud based infrastructure."}, "datasets": [{"viewCount": 167, "name": "Continuity of Operations - Important Files", "nrow": 5, "id": "6bqr-ydh3", "portal": "opendata.socrata.com", "downloadCount": 145, "ncol": 6, "modifyingViewUid": null, "createdAt": 1279586535, "description": "These are critical files that we need backed up offsite. We're using Socrata's cloud based infrastructure."}]}