{"source": {"viewCount": 604, "name": "Water - Shape", "nrow": 0, "id": "fgsy-8jrm", "portal": "data.baltimorecity.gov", "downloadCount": 424, "ncol": 0, "modifyingViewUid": null, "createdAt": 1295795570, "description": "Polygon feature representing photogrammetrically captured hydrographic information, including lakes, ponds, harbors, waterways, reservoirs, and hidden hydrography used to provide continuous topology. Last Updated 2008"}, "datasets": [{"viewCount": 604, "name": "Water - Shape", "nrow": 0, "id": "fgsy-8jrm", "portal": "data.baltimorecity.gov", "downloadCount": 424, "ncol": 0, "modifyingViewUid": null, "createdAt": 1295795570, "description": "Polygon feature representing photogrammetrically captured hydrographic information, including lakes, ponds, harbors, waterways, reservoirs, and hidden hydrography used to provide continuous topology. Last Updated 2008"}]}