{"source": {"viewCount": 4288, "name": "FEMA Public Assistance Funded Projects Summary", "nrow": 0, "id": "btjd-2xvr", "portal": "data.oregon.gov", "downloadCount": 3110, "ncol": 0, "modifyingViewUid": null, "createdAt": 1298048125, "description": "Through the PA Program (CDFA Number 97.036), FEMA provides supplemental Federal disaster grant assistance for debris removal, emergency protective measures, and the repair, replacement, or restoration of disaster-damaged, publicly owned facilities and the facilities of certain Private Non-Profit (PNP) organizations. The PA Program also encourages protection of these damaged facilities from future events by providing assistance for hazard mitigation measures during the recovery process. FEMA is very active in rebuilding communities through public facilities as well as individual homes and property. This dataset lists all public assistance recipients (subgrantees) and a summary of the funded program support."}, "datasets": [{"viewCount": 4288, "name": "FEMA Public Assistance Funded Projects Summary", "nrow": 0, "id": "btjd-2xvr", "portal": "data.oregon.gov", "downloadCount": 3110, "ncol": 0, "modifyingViewUid": null, "createdAt": 1298048125, "description": "Through the PA Program (CDFA Number 97.036), FEMA provides supplemental Federal disaster grant assistance for debris removal, emergency protective measures, and the repair, replacement, or restoration of disaster-damaged, publicly owned facilities and the facilities of certain Private Non-Profit (PNP) organizations. The PA Program also encourages protection of these damaged facilities from future events by providing assistance for hazard mitigation measures during the recovery process. FEMA is very active in rebuilding communities through public facilities as well as individual homes and property. This dataset lists all public assistance recipients (subgrantees) and a summary of the funded program support."}]}