{"source": {"viewCount": 426, "name": "RSS Feeds for Storm Prediction Center Severe Weather Outlooks, Watches, Discussions, and Status Reports", "nrow": 0, "id": "69ry-stgt", "portal": "data.oregon.gov", "downloadCount": 361, "ncol": 0, "modifyingViewUid": null, "createdAt": 1298048317, "description": "The  National Weather  Service (NWS)  Storm Prediction Center uses RSS feeds to disseminate severe weather outlooks and watches, mesoscale discussion, and status reports.   These RSS feeds are regularly updated and include the following :  tornado/severe thunderstorm watches; mesoscale discussions; convective outlooks;  and fire weather outlooks."}, "datasets": [{"viewCount": 426, "name": "RSS Feeds for Storm Prediction Center Severe Weather Outlooks, Watches, Discussions, and Status Reports", "nrow": 0, "id": "69ry-stgt", "portal": "data.oregon.gov", "downloadCount": 361, "ncol": 0, "modifyingViewUid": null, "createdAt": 1298048317, "description": "The  National Weather  Service (NWS)  Storm Prediction Center uses RSS feeds to disseminate severe weather outlooks and watches, mesoscale discussion, and status reports.   These RSS feeds are regularly updated and include the following :  tornado/severe thunderstorm watches; mesoscale discussions; convective outlooks;  and fire weather outlooks."}]}