{"source": {"viewCount": 175, "name": "Supplement to the President's Budget. Estimates & Request for Agency NITRD budget.", "nrow": 0, "id": "fdaf-2efb", "portal": "data.oregon.gov", "downloadCount": 186, "ncol": 0, "modifyingViewUid": null, "createdAt": 1298048878, "description": "This dataset  presents the aggregated Networking and Information Technology Research and Development (NITRD) program across 13 Federal agencies produced by the National Coordination Office (NCO)."}, "datasets": [{"viewCount": 175, "name": "Supplement to the President's Budget. Estimates & Request for Agency NITRD budget.", "nrow": 0, "id": "fdaf-2efb", "portal": "data.oregon.gov", "downloadCount": 186, "ncol": 0, "modifyingViewUid": null, "createdAt": 1298048878, "description": "This dataset  presents the aggregated Networking and Information Technology Research and Development (NITRD) program across 13 Federal agencies produced by the National Coordination Office (NCO)."}]}