{"source": {"viewCount": 375, "name": "Average US State Electricity Rates 2011", "nrow": 59, "id": "itr5-inf8", "portal": "opendata.socrata.com", "downloadCount": 3, "ncol": 3, "modifyingViewUid": null, "createdAt": 1306263433, "description": "These are the average 2011 electricity rates by state."}, "datasets": [{"viewCount": 110, "name": "US Electric Rates Average 2011", "nrow": 59, "id": "t5ih-c39m", "portal": "opendata.socrata.com", "downloadCount": 4, "ncol": 3, "modifyingViewUid": null, "createdAt": 1306269973, "description": "These are the average 2011 electricity rates by state."}, {"viewCount": 375, "name": "Average US State Electricity Rates 2011", "nrow": 59, "id": "itr5-inf8", "portal": "opendata.socrata.com", "downloadCount": 3, "ncol": 3, "modifyingViewUid": null, "createdAt": 1306263433, "description": "These are the average 2011 electricity rates by state."}]}