{"source": {"viewCount": 110, "name": "Percentage Distribution of Households by Reasons for borrowing, County estimates - 2005/6", "nrow": 48, "id": "dc8c-zj5z", "portal": "opendata.go.ke", "downloadCount": 28, "ncol": 13, "modifyingViewUid": null, "createdAt": 1309402851, "description": "KIHBS Table 8.8: Percentage Distribution of Households by Reasons for borrowing, County estimates"}, "datasets": [{"viewCount": 110, "name": "Percentage Distribution of Households by Reasons for borrowing, County estimates - 2005/6", "nrow": 48, "id": "dc8c-zj5z", "portal": "opendata.go.ke", "downloadCount": 28, "ncol": 13, "modifyingViewUid": null, "createdAt": 1309402851, "description": "KIHBS Table 8.8: Percentage Distribution of Households by Reasons for borrowing, County estimates"}]}