{"source": {"viewCount": 475, "name": "Quarterly Financial Report", "nrow": 0, "id": "8hdu-ip3v", "portal": "data.oregon.gov", "downloadCount": 294, "ncol": 0, "modifyingViewUid": null, "createdAt": 1309890330, "description": "Series that provides national economic data for Manufacturing, Mining, Trade, and Selected Service Corporations. The QFR data are widely used by government agencies, domestic and foreign businesses, financial analysts, researchers, trade associations, and banking institutions. Uses include assessing industrial debt structure, liquidity, and profitability; estimating corporate tax liability; designing economic policies and drafting legislation; making investment evaluations; and studying economic trends."}, "datasets": [{"viewCount": 475, "name": "Quarterly Financial Report", "nrow": 0, "id": "8hdu-ip3v", "portal": "data.oregon.gov", "downloadCount": 294, "ncol": 0, "modifyingViewUid": null, "createdAt": 1309890330, "description": "Series that provides national economic data for Manufacturing, Mining, Trade, and Selected Service Corporations. The QFR data are widely used by government agencies, domestic and foreign businesses, financial analysts, researchers, trade associations, and banking institutions. Uses include assessing industrial debt structure, liquidity, and profitability; estimating corporate tax liability; designing economic policies and drafting legislation; making investment evaluations; and studying economic trends."}]}