{"source": {"viewCount": 28, "name": "Environmental Control--2010 Energy Audits", "nrow": 249, "id": "gb3h-yccn", "portal": "www.metrochicagodata.org", "downloadCount": 3, "ncol": 8, "modifyingViewUid": null, "createdAt": 1316526198, "description": "Locations and detail of energy audit projects"}, "datasets": [{"viewCount": 28, "name": "Environmental Control--2010 Energy Audits", "nrow": 249, "id": "gb3h-yccn", "portal": "www.metrochicagodata.org", "downloadCount": 3, "ncol": 8, "modifyingViewUid": null, "createdAt": 1316526198, "description": "Locations and detail of energy audit projects"}]}