{"source": {"viewCount": 57, "name": "Export-Import FY 2009 Participants", "nrow": 0, "id": "hvtk-gqmi", "portal": "data.oregon.gov", "downloadCount": 132, "ncol": 0, "modifyingViewUid": null, "createdAt": 1317420372, "description": "This file contains companies and individuals (participants) on applications that were approved or denied/declined during fiscal year 2009. The participant roles on the related deals that are included in this dataset are: Applicant, Borrower, Buyer, Exporter, Guaranteed Lender, Guarantor, Insured, PSOR (Primary Source of Repayment), and Supplier.  Participants can be linked to deals in the deal level data set for the same fiscal year by the value in the Unique Identifier column. Note that there will typically be more than one participant associated with each deal."}, "datasets": [{"viewCount": 57, "name": "Export-Import FY 2009 Participants", "nrow": 0, "id": "hvtk-gqmi", "portal": "data.oregon.gov", "downloadCount": 132, "ncol": 0, "modifyingViewUid": null, "createdAt": 1317420372, "description": "This file contains companies and individuals (participants) on applications that were approved or denied/declined during fiscal year 2009. The participant roles on the related deals that are included in this dataset are: Applicant, Borrower, Buyer, Exporter, Guaranteed Lender, Guarantor, Insured, PSOR (Primary Source of Repayment), and Supplier.  Participants can be linked to deals in the deal level data set for the same fiscal year by the value in the Unique Identifier column. Note that there will typically be more than one participant associated with each deal."}]}