{"source": {"viewCount": 68, "name": "Guam Schools - Map", "nrow": 43, "id": "izr6-yndv", "portal": "opendata.socrata.com", "downloadCount": 9, "ncol": 16, "modifyingViewUid": null, "createdAt": 1320027087, "description": null}, "datasets": [{"viewCount": 68, "name": "Guam Schools - Map", "nrow": 43, "id": "izr6-yndv", "portal": "opendata.socrata.com", "downloadCount": 9, "ncol": 16, "modifyingViewUid": null, "createdAt": 1320027087, "description": null}, {"viewCount": 17, "name": "Guam Schools - Map", "nrow": 43, "id": "xj5n-aadp", "portal": "opendata.socrata.com", "downloadCount": 4, "ncol": 16, "modifyingViewUid": null, "createdAt": 1320026926, "description": null}]}