{"source": {"viewCount": 8, "name": "Area Chart -- Divorce Filings", "nrow": 29, "id": "s6wf-zwwn", "portal": "opendata.socrata.com", "downloadCount": 1, "ncol": 2, "modifyingViewUid": null, "createdAt": 1321302083, "description": "The Tribune's data website UtahsRight and Close-Up gives you a weekly statistical look at your communities. More details on divorce records and other information about where yo live are available at UtahsRight.com."}, "datasets": [{"viewCount": 8, "name": "Area Chart -- Divorce Filings", "nrow": 29, "id": "s6wf-zwwn", "portal": "opendata.socrata.com", "downloadCount": 1, "ncol": 2, "modifyingViewUid": null, "createdAt": 1321302083, "description": "The Tribune's data website UtahsRight and Close-Up gives you a weekly statistical look at your communities. More details on divorce records and other information about where yo live are available at UtahsRight.com."}]}