{"source": {"viewCount": 86, "name": "Black Friday Deals 2011", "nrow": 14870, "id": "mw9b-ny4y", "portal": "opendata.socrata.com", "downloadCount": 279, "ncol": 8, "modifyingViewUid": null, "createdAt": 1321973866, "description": "Black Friday Deals 2011"}, "datasets": [{"viewCount": 86, "name": "Black Friday Deals 2011", "nrow": 14870, "id": "mw9b-ny4y", "portal": "opendata.socrata.com", "downloadCount": 279, "ncol": 8, "modifyingViewUid": null, "createdAt": 1321973866, "description": "Black Friday Deals 2011"}]}