{"source": {"viewCount": 191, "name": "Monuments", "nrow": 84, "id": "cpxf-kxp3", "portal": "data.baltimorecity.gov", "downloadCount": 76, "ncol": 6, "modifyingViewUid": null, "createdAt": 1323887241, "description": "This data set shows the point location of Baltimore City monuments. However, the completness and currentness of these data are uncertain."}, "datasets": [{"viewCount": 191, "name": "Monuments", "nrow": 84, "id": "cpxf-kxp3", "portal": "data.baltimorecity.gov", "downloadCount": 76, "ncol": 6, "modifyingViewUid": null, "createdAt": 1323887241, "description": "This data set shows the point location of Baltimore City monuments. However, the completness and currentness of these data are uncertain."}]}