{"source": {"viewCount": 7, "name": "Nuevos Establecimientos de Salud - Presupuesto 2012", "nrow": 77, "id": "askn-36y3", "portal": "opendata.socrata.com", "downloadCount": 1, "ncol": 2, "modifyingViewUid": null, "createdAt": 1327503080, "description": "Presupuesto de Inversi\u00f3n para la construccion de los nuevos establecimientos de salud - Registro 2012"}, "datasets": [{"viewCount": 53, "name": "Monto de Inversi\u00f3n de los nuevos EESS", "nrow": 77, "id": "xx9s-a85j", "portal": "opendata.socrata.com", "downloadCount": 2, "ncol": 2, "modifyingViewUid": null, "createdAt": 1327503344, "description": "Presupuesto de Inversi\u00f3n para la construccion de los nuevos establecimientos de salud - Registro 2012"}, {"viewCount": 7, "name": "Nuevos Establecimientos de Salud - Presupuesto 2012", "nrow": 77, "id": "askn-36y3", "portal": "opendata.socrata.com", "downloadCount": 1, "ncol": 2, "modifyingViewUid": null, "createdAt": 1327503080, "description": "Presupuesto de Inversi\u00f3n para la construccion de los nuevos establecimientos de salud - Registro 2012"}]}