{"source": {"viewCount": 542, "name": "ISP - Firearm Owners' Identification (FOID) Applications", "nrow": 10, "id": "vvq4-faea", "portal": "www.metrochicagodata.org", "downloadCount": 10, "ncol": 2, "modifyingViewUid": null, "createdAt": 1328051028, "description": "FOID Card Applications -- 10 Year History -- 2002 through 2011"}, "datasets": [{"viewCount": 542, "name": "ISP - Firearm Owners' Identification (FOID) Applications", "nrow": 10, "id": "vvq4-faea", "portal": "www.metrochicagodata.org", "downloadCount": 10, "ncol": 2, "modifyingViewUid": null, "createdAt": 1328051028, "description": "FOID Card Applications -- 10 Year History -- 2002 through 2011"}]}