{"source": {"viewCount": 51, "name": "IDOR December 2011 Disbursement Info", "nrow": 2026, "id": "nz4r-xryt", "portal": "www.metrochicagodata.org", "downloadCount": 8, "ncol": 5, "modifyingViewUid": null, "createdAt": 1332967842, "description": "Contains disbursement information for the October 2011 collections of Sales and Related Taxes.  Voucher Date: 12/07/2011"}, "datasets": [{"viewCount": 51, "name": "IDOR December 2011 Disbursement Info", "nrow": 2026, "id": "nz4r-xryt", "portal": "www.metrochicagodata.org", "downloadCount": 8, "ncol": 5, "modifyingViewUid": null, "createdAt": 1332967842, "description": "Contains disbursement information for the October 2011 collections of Sales and Related Taxes.  Voucher Date: 12/07/2011"}]}