{"source": {"viewCount": 1362, "name": "SFGIS Data Catalog - Internal", "nrow": 116, "id": "udj9-yye5", "portal": "data.sfgov.org", "downloadCount": 168, "ncol": 5, "modifyingViewUid": null, "createdAt": 1342568391, "description": "SFGIS Data Catalog - Internal"}, "datasets": [{"viewCount": 1362, "name": "SFGIS Data Catalog - Internal", "nrow": 116, "id": "udj9-yye5", "portal": "data.sfgov.org", "downloadCount": 168, "ncol": 5, "modifyingViewUid": null, "createdAt": 1342568391, "description": "SFGIS Data Catalog - Internal"}, {"viewCount": 83, "name": "Source Orgs for internal data catalog", "nrow": 24, "id": "mbhu-iuiq", "portal": "data.sfgov.org", "downloadCount": 6, "ncol": 1, "modifyingViewUid": null, "createdAt": 1344361905, "description": "SFGIS Data Catalog - Internal"}]}