{"source": {"viewCount": 207, "name": "Performance Metrics - Chicago Park District - Natural Resources Trees and Shrubs", "nrow": 54, "id": "cnj6-r3qn", "portal": "www.metrochicagodata.org", "downloadCount": 19, "ncol": 6, "modifyingViewUid": null, "createdAt": 1322253603, "description": "The Department of Natural Resources (CDNR) was created in 2001 and is responsible for ensuring the quality of the district's 7,300 acres of land. Through enhanced landscape management, staff training and constant high quality maintenance, the department is quickly becoming the benchmark by which many municipal organizations measure the quality of their landscape and gardening. The data below represents the number of trees that were removed District-wide as well as the number of shrubs and trees that were pruned."}, "datasets": [{"viewCount": 207, "name": "Performance Metrics - Chicago Park District - Natural Resources Trees and Shrubs", "nrow": 54, "id": "cnj6-r3qn", "portal": "www.metrochicagodata.org", "downloadCount": 19, "ncol": 6, "modifyingViewUid": null, "createdAt": 1322253603, "description": "The Department of Natural Resources (CDNR) was created in 2001 and is responsible for ensuring the quality of the district's 7,300 acres of land. Through enhanced landscape management, staff training and constant high quality maintenance, the department is quickly becoming the benchmark by which many municipal organizations measure the quality of their landscape and gardening. The data below represents the number of trees that were removed District-wide as well as the number of shrubs and trees that were pruned."}]}