{"source": {"viewCount": 233, "name": "Column Chart: VR/Welfare Partnerships - APSE", "nrow": 1, "id": "qsas-5jbv", "portal": "opendata.socrata.com", "downloadCount": 0, "ncol": 11, "modifyingViewUid": null, "createdAt": 1337963286, "description": null}, "datasets": [{"viewCount": 233, "name": "Column Chart: VR/Welfare Partnerships - APSE", "nrow": 1, "id": "qsas-5jbv", "portal": "opendata.socrata.com", "downloadCount": 0, "ncol": 11, "modifyingViewUid": null, "createdAt": 1337963286, "description": null}, {"viewCount": 7, "name": "Data: VR/Welfare Partnerships - APSE", "nrow": 1, "id": "fcxs-tw5y", "portal": "opendata.socrata.com", "downloadCount": 0, "ncol": 13, "modifyingViewUid": null, "createdAt": 1337963047, "description": null}]}