{"source": {"viewCount": 112, "name": "secretary of state - 5th Legislative District", "nrow": 8, "id": "htei-v2tk", "portal": "data.kingcounty.gov", "downloadCount": 22, "ncol": 2, "modifyingViewUid": null, "createdAt": 1347411554, "description": "Cumulative eCanvass for King County Elections, August 7 2012 primary"}, "datasets": [{"viewCount": 112, "name": "secretary of state - 5th Legislative District", "nrow": 8, "id": "htei-v2tk", "portal": "data.kingcounty.gov", "downloadCount": 22, "ncol": 2, "modifyingViewUid": null, "createdAt": 1347411554, "description": "Cumulative eCanvass for King County Elections, August 7 2012 primary"}, {"viewCount": 716, "name": "Tina Precincts", "nrow": 980, "id": "g4jr-cb8e", "portal": "data.kingcounty.gov", "downloadCount": 18, "ncol": 9, "modifyingViewUid": null, "createdAt": 1346386534, "description": "Cumulative eCanvass for King County Elections, August 7 2012 primary"}]}