{"source": {"viewCount": 2302, "name": "Bronx 311 School Suspension Discipline", "nrow": 108, "id": "awwe-zymn", "portal": "bronx.lehman.cuny.edu", "downloadCount": 19, "ncol": 34, "modifyingViewUid": null, "createdAt": 1347555723, "description": "311 Data on the number of suspensions and disciplinary actions in Bronx schools"}, "datasets": [{"viewCount": 2302, "name": "Bronx 311 School Suspension Discipline", "nrow": 108, "id": "awwe-zymn", "portal": "bronx.lehman.cuny.edu", "downloadCount": 19, "ncol": 34, "modifyingViewUid": null, "createdAt": 1347555723, "description": "311 Data on the number of suspensions and disciplinary actions in Bronx schools"}]}