{"source": {"viewCount": 648, "name": "Hospitals Map", "nrow": 15, "id": "qtub-p7bm", "portal": "data.montgomerycountymd.gov", "downloadCount": 24, "ncol": 10, "modifyingViewUid": null, "createdAt": 1330464611, "description": "Address and Locations for Hospitals in Montgomery County, MD and the immediate vicinity."}, "datasets": [{"viewCount": 97, "name": "Hospitals", "nrow": 15, "id": "677d-kzp6", "portal": "data.montgomerycountymd.gov", "downloadCount": 19, "ncol": 10, "modifyingViewUid": null, "createdAt": 1330464168, "description": "Address and Locations for Hospitals in Montgomery County, MD and the immediate vicinity."}, {"viewCount": 648, "name": "Hospitals Map", "nrow": 15, "id": "qtub-p7bm", "portal": "data.montgomerycountymd.gov", "downloadCount": 24, "ncol": 10, "modifyingViewUid": null, "createdAt": 1330464611, "description": "Address and Locations for Hospitals in Montgomery County, MD and the immediate vicinity."}]}