{"source": {"viewCount": 50, "name": "ENERGY STAR Qualified New Vending Machines", "nrow": 0, "id": "hhke-kxyn", "portal": "data.oregon.gov", "downloadCount": 68, "ncol": 0, "modifyingViewUid": null, "createdAt": 1350312947, "description": "New Vending Machines that have earned the ENERGY STAR are more efficient than standard models. ENERGY STAR is the trusted symbol for energy efficiency helping consumers save money and protect the environment through energy-efficient products and practices.  More information on ENERGY STAR is available at www.energystar.gov."}, "datasets": [{"viewCount": 50, "name": "ENERGY STAR Qualified New Vending Machines", "nrow": 0, "id": "hhke-kxyn", "portal": "data.oregon.gov", "downloadCount": 68, "ncol": 0, "modifyingViewUid": null, "createdAt": 1350312947, "description": "New Vending Machines that have earned the ENERGY STAR are more efficient than standard models. ENERGY STAR is the trusted symbol for energy efficiency helping consumers save money and protect the environment through energy-efficient products and practices.  More information on ENERGY STAR is available at www.energystar.gov."}]}