{"source": {"viewCount": 42, "name": "Vegetated Area", "nrow": 0, "id": "rqna-ikwn", "portal": "data.baltimorecity.gov", "downloadCount": 0, "ncol": 0, "modifyingViewUid": null, "createdAt": 1350932054, "description": "Polygon feature representing photogrammetrically captured vegetation features such as wooded/brush areas, tree rows of 50ft or greater in length. Last Updated 2008"}, "datasets": [{"viewCount": 42, "name": "Vegetated Area", "nrow": 0, "id": "rqna-ikwn", "portal": "data.baltimorecity.gov", "downloadCount": 0, "ncol": 0, "modifyingViewUid": null, "createdAt": 1350932054, "description": "Polygon feature representing photogrammetrically captured vegetation features such as wooded/brush areas, tree rows of 50ft or greater in length. Last Updated 2008"}]}