{"source": {"viewCount": 6, "name": "2000 Population of KC Metro Area Cities and Counties", "nrow": 0, "id": "wxxx-rjng", "portal": "data.mo.gov", "downloadCount": 8, "ncol": 0, "modifyingViewUid": null, "createdAt": 1355502884, "description": "population for each city and county"}, "datasets": [{"viewCount": 6, "name": "2000 Population of KC Metro Area Cities and Counties", "nrow": 0, "id": "wxxx-rjng", "portal": "data.mo.gov", "downloadCount": 8, "ncol": 0, "modifyingViewUid": null, "createdAt": 1355502884, "description": "population for each city and county"}]}