{"source": {"viewCount": 183, "name": "Burglary view 2012", "nrow": 147, "id": "bhnf-h45q", "portal": "opendata.socrata.com", "downloadCount": 2, "ncol": 1, "modifyingViewUid": null, "createdAt": 1357164689, "description": null}, "datasets": [{"viewCount": 183, "name": "Burglary view 2012", "nrow": 147, "id": "bhnf-h45q", "portal": "opendata.socrata.com", "downloadCount": 2, "ncol": 1, "modifyingViewUid": null, "createdAt": 1357164689, "description": null}, {"viewCount": 8, "name": "Burglary Map", "nrow": 147, "id": "9mcd-j9ux", "portal": "opendata.socrata.com", "downloadCount": 1, "ncol": 1, "modifyingViewUid": null, "createdAt": 1357599932, "description": null}, {"viewCount": 9, "name": "Map 2012", "nrow": 147, "id": "er5g-jqpj", "portal": "opendata.socrata.com", "downloadCount": 0, "ncol": 2, "modifyingViewUid": null, "createdAt": 1369953858, "description": null}, {"viewCount": 9, "name": "Burglary List 2012--", "nrow": 147, "id": "6z4z-cw6g", "portal": "opendata.socrata.com", "downloadCount": 1, "ncol": 2, "modifyingViewUid": null, "createdAt": 1357163634, "description": null}, {"viewCount": 4, "name": "Payson's burglaries in 2012", "nrow": 147, "id": "kpsn-pktx", "portal": "opendata.socrata.com", "downloadCount": 1, "ncol": 1, "modifyingViewUid": null, "createdAt": 1357599820, "description": null}]}