{"source": {"viewCount": 29, "name": "Tasks by Priority", "nrow": 10, "id": "kyfs-adak", "portal": "opendata.socrata.com", "downloadCount": 17, "ncol": 4, "modifyingViewUid": null, "createdAt": 1210258041, "description": null}, "datasets": [{"viewCount": 29, "name": "Tasks by Priority", "nrow": 10, "id": "kyfs-adak", "portal": "opendata.socrata.com", "downloadCount": 17, "ncol": 4, "modifyingViewUid": null, "createdAt": 1210258041, "description": null}, {"viewCount": 40, "name": "Project List", "nrow": 10, "id": "degn-cshj", "portal": "opendata.socrata.com", "downloadCount": 86, "ncol": 5, "modifyingViewUid": null, "createdAt": 1210256174, "description": null}, {"viewCount": 9, "name": "Job Type", "nrow": 10, "id": "7h6b-6a2a", "portal": "opendata.socrata.com", "downloadCount": 4, "ncol": 4, "modifyingViewUid": null, "createdAt": 1210260717, "description": null}]}