{"source": {"viewCount": 17, "name": "Boston By The Numbers: Families", "nrow": 0, "id": "gnb2-nybf", "portal": "data.cityofboston.gov", "downloadCount": 10, "ncol": 0, "modifyingViewUid": null, "createdAt": 1361999286, "description": "Boston by the Numbers is a series created by the BRA Research Division that highlights the characteristics of Boston's population and economy. This report highlights Boston's families."}, "datasets": [{"viewCount": 17, "name": "Boston By The Numbers: Families", "nrow": 0, "id": "gnb2-nybf", "portal": "data.cityofboston.gov", "downloadCount": 10, "ncol": 0, "modifyingViewUid": null, "createdAt": 1361999286, "description": "Boston by the Numbers is a series created by the BRA Research Division that highlights the characteristics of Boston's population and economy. This report highlights Boston's families."}]}