{"source": {"viewCount": 6, "name": "Web Design and Development", "nrow": 0, "id": "ugr6-na4e", "portal": "opendata.socrata.com", "downloadCount": 1, "ncol": 0, "modifyingViewUid": null, "createdAt": 1363428758, "description": "Computer graphics is very useful and this is prominent due to our daily observations\u2026."}, "datasets": [{"viewCount": 6, "name": "Web Design and Development", "nrow": 0, "id": "ugr6-na4e", "portal": "opendata.socrata.com", "downloadCount": 1, "ncol": 0, "modifyingViewUid": null, "createdAt": 1363428758, "description": "Computer graphics is very useful and this is prominent due to our daily observations\u2026."}]}