{"source": {"viewCount": 17, "name": "New Detached Single Family Dwellings", "nrow": 799, "id": "krh7-ic75", "portal": "data.raleighnc.gov", "downloadCount": 0, "ncol": 24, "modifyingViewUid": null, "createdAt": 1364839722, "description": "Permit data with parcel ID for 2012 and up to 02/08/2013"}, "datasets": [{"viewCount": 20, "name": "Detached Single Family Dwellings", "nrow": 800, "id": "btuy-wked", "portal": "data.raleighnc.gov", "downloadCount": 0, "ncol": 24, "modifyingViewUid": null, "createdAt": 1364839638, "description": "Permit data with parcel ID for 2012 and up to 02/08/2013"}, {"viewCount": 49, "name": "Top Contractors by Number of Permits", "nrow": 1713, "id": "npfs-9ite", "portal": "data.raleighnc.gov", "downloadCount": 0, "ncol": 24, "modifyingViewUid": null, "createdAt": 1365735214, "description": "Permit data with parcel ID for 2012 and up to 02/08/2013"}, {"viewCount": 122, "name": "Building Permits with Parcel ID", "nrow": 5708, "id": "b9nv-68kk", "portal": "data.raleighnc.gov", "downloadCount": 8, "ncol": 24, "modifyingViewUid": null, "createdAt": 1364241410, "description": "Permit data with parcel ID for 2012 and up to 02/08/2013"}, {"viewCount": 160, "name": "Building Permits with Parcel ID Heat Map", "nrow": 5708, "id": "jzdr-6ret", "portal": "data.raleighnc.gov", "downloadCount": 4, "ncol": 24, "modifyingViewUid": null, "createdAt": 1364407102, "description": "Permit data with parcel ID for 2012 and up to 02/08/2013"}, {"viewCount": 45, "name": "Map of Building Permit Data with Parcel ID", "nrow": 5708, "id": "c5dy-pk9x", "portal": "data.raleighnc.gov", "downloadCount": 1, "ncol": 24, "modifyingViewUid": null, "createdAt": 1364406015, "description": "Permit data with parcel ID for 2012 and up to 02/08/2013"}, {"viewCount": 17, "name": "New Detached Single Family Dwellings", "nrow": 799, "id": "krh7-ic75", "portal": "data.raleighnc.gov", "downloadCount": 0, "ncol": 24, "modifyingViewUid": null, "createdAt": 1364839722, "description": "Permit data with parcel ID for 2012 and up to 02/08/2013"}]}