{"source": {"viewCount": 273, "name": "Afghanistan Reconstruction Trust Fund Acronyms - Pilot", "nrow": 73, "id": "fjye-9bys", "portal": "finances.worldbank.org", "downloadCount": 16, "ncol": 2, "modifyingViewUid": null, "createdAt": 1362760162, "description": "The Afghanistan Reconstruction Trust Fund (ARTF) generates a quarterly report to Donors. This dataset represents acronyms defined in the quarterly report, and are applicable to the ARTF program as a whole."}, "datasets": [{"viewCount": 273, "name": "Afghanistan Reconstruction Trust Fund Acronyms - Pilot", "nrow": 73, "id": "fjye-9bys", "portal": "finances.worldbank.org", "downloadCount": 16, "ncol": 2, "modifyingViewUid": null, "createdAt": 1362760162, "description": "The Afghanistan Reconstruction Trust Fund (ARTF) generates a quarterly report to Donors. This dataset represents acronyms defined in the quarterly report, and are applicable to the ARTF program as a whole."}]}