{"source": {"viewCount": 5, "name": "NTSB Curbside Bus Fatalities For Open Data", "nrow": 40, "id": "yr3v-t22f", "portal": "opendata.socrata.com", "downloadCount": 0, "ncol": 9, "modifyingViewUid": null, "createdAt": 1367326437, "description": "A list of fatal accidents involving bus companies that were classified by the National Transportation Safety Board as \"Curbside Carriers\" in its 2011 \"Report on Motorcoach Safety.\""}, "datasets": [{"viewCount": 5, "name": "NTSB Curbside Bus Fatalities For Open Data", "nrow": 40, "id": "yr3v-t22f", "portal": "opendata.socrata.com", "downloadCount": 0, "ncol": 9, "modifyingViewUid": null, "createdAt": 1367326437, "description": "A list of fatal accidents involving bus companies that were classified by the National Transportation Safety Board as \"Curbside Carriers\" in its 2011 \"Report on Motorcoach Safety.\""}]}