{"source": {"viewCount": 28, "name": "USDA Database for the Isoflavone Content of Selected Foods, Release 2.0", "nrow": 0, "id": "278i-hy2a", "portal": "data.oregon.gov", "downloadCount": 19, "ncol": 0, "modifyingViewUid": null, "createdAt": 1367418428, "description": "This database contains data on the isoflavone content of 557 food items. Isoflavones included in the database are daidzein, genistein, glycitein and total isoflavones. Other phytoestrogens included in the database are coumestrol, biochanin A, and formononetin."}, "datasets": [{"viewCount": 28, "name": "USDA Database for the Isoflavone Content of Selected Foods, Release 2.0", "nrow": 0, "id": "278i-hy2a", "portal": "data.oregon.gov", "downloadCount": 19, "ncol": 0, "modifyingViewUid": null, "createdAt": 1367418428, "description": "This database contains data on the isoflavone content of 557 food items. Isoflavones included in the database are daidzein, genistein, glycitein and total isoflavones. Other phytoestrogens included in the database are coumestrol, biochanin A, and formononetin."}]}