{"source": {"viewCount": 29, "name": "testing", "nrow": 0, "id": "kr2e-xfqx", "portal": "opendata.socrata.com", "downloadCount": 87, "ncol": 5, "modifyingViewUid": null, "createdAt": 1230017188, "description": null}, "datasets": [{"viewCount": 32, "name": "NetSafe", "nrow": 0, "id": "2z34-8wsb", "portal": "opendata.socrata.com", "downloadCount": 84, "ncol": 5, "modifyingViewUid": null, "createdAt": 1222454417, "description": null}, {"viewCount": 23, "name": "test lens", "nrow": 0, "id": "7pkf-7f3u", "portal": "opendata.socrata.com", "downloadCount": 111, "ncol": 5, "modifyingViewUid": null, "createdAt": 1229163167, "description": null}, {"viewCount": 91, "name": "Project Template", "nrow": 0, "id": "4wih-ttm4", "portal": "opendata.socrata.com", "downloadCount": 54, "ncol": 6, "modifyingViewUid": null, "createdAt": 1218323373, "description": null}, {"viewCount": 39, "name": "hoho", "nrow": 0, "id": "3iby-2xtw", "portal": "opendata.socrata.com", "downloadCount": 96, "ncol": 5, "modifyingViewUid": null, "createdAt": 1229163831, "description": null}, {"viewCount": 29, "name": "testing", "nrow": 0, "id": "kr2e-xfqx", "portal": "opendata.socrata.com", "downloadCount": 87, "ncol": 5, "modifyingViewUid": null, "createdAt": 1230017188, "description": null}]}