{"source": {"viewCount": 8, "name": "Chicago Crimes 36k", "nrow": 38721, "id": "k9uu-pfac", "portal": "opendata.socrata.com", "downloadCount": 0, "ncol": 20, "modifyingViewUid": null, "createdAt": 1370392592, "description": null}, "datasets": [{"viewCount": 8, "name": "Chicago Crimes 36k", "nrow": 38721, "id": "k9uu-pfac", "portal": "opendata.socrata.com", "downloadCount": 0, "ncol": 20, "modifyingViewUid": null, "createdAt": 1370392592, "description": null}, {"viewCount": 2, "name": "Chicago Crime Map", "nrow": 38721, "id": "4fuu-thu9", "portal": "opendata.socrata.com", "downloadCount": 0, "ncol": 20, "modifyingViewUid": null, "createdAt": 1370446320, "description": null}]}