{"source": {"viewCount": 1, "name": "Parks & Rec - Recreation FY13 Adopted - Donut Chart", "nrow": 6, "id": "r89p-f839", "portal": "data.raleighnc.gov", "downloadCount": 0, "ncol": 3, "modifyingViewUid": null, "createdAt": 1371150732, "description": "Parks & Rec - Recreation FY13 Adopted And FY14 Proposed Budgets"}, "datasets": [{"viewCount": 1, "name": "Parks & Rec - Recreation FY13 Adopted - Donut Chart", "nrow": 6, "id": "r89p-f839", "portal": "data.raleighnc.gov", "downloadCount": 0, "ncol": 3, "modifyingViewUid": null, "createdAt": 1371150732, "description": "Parks & Rec - Recreation FY13 Adopted And FY14 Proposed Budgets"}, {"viewCount": 1, "name": "Parks & Rec - Recreation FY13 Adopted - Bubble Chart", "nrow": 6, "id": "b2yj-vzp5", "portal": "data.raleighnc.gov", "downloadCount": 0, "ncol": 3, "modifyingViewUid": null, "createdAt": 1371150572, "description": "Parks & Rec - Recreation FY13 Adopted And FY14 Proposed Budgets"}, {"viewCount": 6, "name": "Parks & Rec - Recreation", "nrow": 1540, "id": "pi8f-ungr", "portal": "data.raleighnc.gov", "downloadCount": 0, "ncol": 8, "modifyingViewUid": null, "createdAt": 1370446372, "description": "Parks & Rec - Recreation FY13 Adopted And FY14 Proposed Budgets"}]}