{"source": {"viewCount": 1, "name": "PW-Safelight FY13 Adopted = Bar Chart", "nrow": 5, "id": "vrta-rr5e", "portal": "data.raleighnc.gov", "downloadCount": 0, "ncol": 3, "modifyingViewUid": null, "createdAt": 1371061604, "description": "PW- Safelight FY13 Adopted And FY14 Proposed Budgets"}, "datasets": [{"viewCount": 1, "name": "PW-Safelight FY14 Proposed - Bar Chart", "nrow": 5, "id": "xm93-tg9b", "portal": "data.raleighnc.gov", "downloadCount": 0, "ncol": 3, "modifyingViewUid": null, "createdAt": 1371061676, "description": "PW- Safelight FY13 Adopted And FY14 Proposed Budgets"}, {"viewCount": 1, "name": "PW-Safelight FY13 Adopted - Donut Chart", "nrow": 5, "id": "hrtp-hwz5", "portal": "data.raleighnc.gov", "downloadCount": 0, "ncol": 3, "modifyingViewUid": null, "createdAt": 1371061812, "description": "PW- Safelight FY13 Adopted And FY14 Proposed Budgets"}, {"viewCount": 7, "name": "PW- Safelight", "nrow": 44, "id": "mcdp-6aih", "portal": "data.raleighnc.gov", "downloadCount": 0, "ncol": 8, "modifyingViewUid": null, "createdAt": 1370456054, "description": "PW- Safelight FY13 Adopted And FY14 Proposed Budgets"}, {"viewCount": 1, "name": "PW-Safelight FY14 Proposed - Donut Chart", "nrow": 5, "id": "hfx3-6dfb", "portal": "data.raleighnc.gov", "downloadCount": 0, "ncol": 3, "modifyingViewUid": null, "createdAt": 1371061774, "description": "PW- Safelight FY13 Adopted And FY14 Proposed Budgets"}, {"viewCount": 1, "name": "PW-Safelight FY13 Adopted = Bar Chart", "nrow": 5, "id": "vrta-rr5e", "portal": "data.raleighnc.gov", "downloadCount": 0, "ncol": 3, "modifyingViewUid": null, "createdAt": 1371061604, "description": "PW- Safelight FY13 Adopted And FY14 Proposed Budgets"}]}