{"source": {"viewCount": 5, "name": "Bronx Educational Facilities 311 Complaints pointmap", "nrow": 1589, "id": "f5ky-ffxn", "portal": "bronx.lehman.cuny.edu", "downloadCount": 0, "ncol": 35, "modifyingViewUid": null, "createdAt": 1357831498, "description": "DOE complaints and service requests via 311 database."}, "datasets": [{"viewCount": 5177, "name": "Bronx 311 DOE Requests And Complaints", "nrow": 1589, "id": "7c53-5hp2", "portal": "bronx.lehman.cuny.edu", "downloadCount": 60, "ncol": 35, "modifyingViewUid": null, "createdAt": 1348001180, "description": "DOE complaints and service requests via 311 database."}, {"viewCount": 5, "name": "Bronx Educational Facilities 311 Complaints pointmap", "nrow": 1589, "id": "f5ky-ffxn", "portal": "bronx.lehman.cuny.edu", "downloadCount": 0, "ncol": 35, "modifyingViewUid": null, "createdAt": 1357831498, "description": "DOE complaints and service requests via 311 database."}]}