{"source": {"viewCount": 29, "name": "Attribution of Complaints to Different Bureaus", "nrow": 3, "id": "wwsa-q2dq", "portal": "data.cityofnewyork.us", "downloadCount": 5, "ncol": 16, "modifyingViewUid": null, "createdAt": 1361828503, "description": "This is the table compiled in one data-set from different bureaus representing the attribution of complaints"}, "datasets": [{"viewCount": 29, "name": "Attribution of Complaints to Different Bureaus", "nrow": 3, "id": "wwsa-q2dq", "portal": "data.cityofnewyork.us", "downloadCount": 5, "ncol": 16, "modifyingViewUid": null, "createdAt": 1361828503, "description": "This is the table compiled in one data-set from different bureaus representing the attribution of complaints"}]}