{"source": {"viewCount": 63, "name": "Oil Usage ( Select City Owned Buildings)", "nrow": 65, "id": "whux-iuiu", "portal": "data.cityofnewyork.us", "downloadCount": 10, "ncol": 17, "modifyingViewUid": null, "createdAt": 1346951597, "description": "Oil usage statistics for a select portfolio of City-owned buildings"}, "datasets": [{"viewCount": 63, "name": "Oil Usage ( Select City Owned Buildings)", "nrow": 65, "id": "whux-iuiu", "portal": "data.cityofnewyork.us", "downloadCount": 10, "ncol": 17, "modifyingViewUid": null, "createdAt": 1346951597, "description": "Oil usage statistics for a select portfolio of City-owned buildings"}]}